[
{"pname": "Lahiru Thirimanne", "img": "https://www.cricbuzz.com/a/img/v1/75x75/i1/c170704/lahiru-thirimanne.jpg", "country": "Sri Lanka National Cricket Team "},
{"pname": "Dimuth Karunaratne", "img": "https://www.cricbuzz.com/a/img/v1/75x75/i1/c170700/dimuth-karunaratne.jpg", "country": "Sri Lanka National Cricket Team "},
{"pname": "Avishka Fernando", "img": "https://www.cricbuzz.com/a/img/v1/75x75/i1/c170702/avishka-fernando.jpg", "country": "Sri Lanka National Cricket Team "},
{"pname": "Angelo Mathews", "img": "https://www.cricbuzz.com/a/img/v1/75x75/i1/c170706/angelo-mathews.jpg", "country": "Sri Lanka National Cricket Team "},
{"pname": "Dhananjaya de Silva", "img": "https://www.cricbuzz.com/a/img/v1/75x75/i1/c170708/dhananjaya-de-silva.jpg", "country": "Sri Lanka National Cricket Team "},
{"pname": "Isuru Udana", "img": "https://www.cricbuzz.com/a/img/v1/75x75/i1/c170710/isuru-udana.jpg", "country": "Sri Lanka National Cricket Team "},
{"pname": "Milinda Siriwardana", "img": "https://www.cricbuzz.com/a/img/v1/75x75/i1/c170712/milinda-siriwardana.jpg", "country": "Sri Lanka National Cricket Team "},
{"pname": "Thisara Perera", "img": "https://www.cricbuzz.com/a/img/v1/75x75/i1/c170714/thisara-perera.jpg", "country": "Sri Lanka National Cricket Team "},
{"pname": "Jeevan Mendis", "img": "https://www.cricbuzz.com/a/img/v1/75x75/i1/c170716/jeevan-mendis.jpg", "country": "Sri Lanka National Cricket Team "},
{"pname": "Kusal Perera", "img": "https://www.cricbuzz.com/a/img/v1/75x75/i1/c170718/kusal-perera.jpg", "country": "Sri Lanka National Cricket Team "},
{"pname": "Kusal Mendis", "img": "https://www.cricbuzz.com/a/img/v1/75x75/i1/c170815/kusal-mendis.jpg", "country": "Sri Lanka National Cricket Team "},
{"pname": "Suranga Lakmal", "img": "https://www.cricbuzz.com/a/img/v1/75x75/i1/c170726/suranga-lakmal.jpg", "country": "Sri Lanka National Cricket Team "},
{"pname": "Lasith Malinga", "img": "https://www.cricbuzz.com/a/img/v1/75x75/i1/c170724/lasith-malinga.jpg", "country": "Sri Lanka National Cricket Team "},
{"pname": "Jeffrey Vandersay", "img": "https://www.cricbuzz.com/a/img/v1/75x75/i1/c170722/jeffrey-vandersay.jpg", "country": "Sri Lanka National Cricket Team "},
{"pname": "Nuwan Pradeep", "img": "https://www.cricbuzz.com/a/img/v1/75x75/i1/c170728/nuwan-pradeep.jpg", "country": "Sri Lanka National Cricket Team "},
{"pname": "Darren Bravo", "img": "https://www.cricbuzz.com/a/img/v1/75x75/i1/c170790/darren-bravo.jpg", "country": "West Indies Cricket Team "},
{"pname": "Chris Gayle", "img": "https://www.cricbuzz.com/a/img/v1/75x75/i1/c170801/chris-gayle.jpg", "country": "West Indies Cricket Team "},
{"pname": "Evin Lewis", "img": "https://www.cricbuzz.com/a/img/v1/75x75/i1/c170785/evin-lewis.jpg", "country": "West Indies Cricket Team "},
{"pname": "Shimron Hetmyer", "img": "https://www.cricbuzz.com/a/img/v1/75x75/i1/c171232/shimron-hetmyer.jpg", "country": "West Indies Cricket Team "},
{"pname": "Fabian Allen", "img": "https://www.cricbuzz.com/a/img/v1/75x75/i1/c170794/fabian-allen.jpg", "country": "West Indies Cricket Team "},
{"pname": "Hashim Amla", "img": "https://www.cricbuzz.com/a/img/v1/75x75/i1/c170633/hashim-amla.jpg", "country": "South Africa National Cricket Team "},
{"pname": "Faf du Plessis", "img": "https://www.cricbuzz.com/a/img/v1/75x75/i1/c170639/faf-du-plessis.jpg", "country": "South Africa National Cricket Team "},
{"pname": "David Miller", "img": "https://www.cricbuzz.com/a/img/v1/75x75/i1/c170687/david-miller.jpg", "country": "South Africa National Cricket Team "},
{"pname": "Aiden Markram", "img": "https://www.cricbuzz.com/a/img/v1/75x75/i1/c170645/aiden-markram.jpg", "country": "South Africa National Cricket Team "},
{"pname": "Rassie van der Dussen", "img": "https://www.cricbuzz.com/a/img/v1/75x75/i1/c170691/rassie-van-der-dussen.jpg", "country": "South Africa National Cricket Team "},
{"pname": "Jean-Paul Duminy", "img": "https://www.cricbuzz.com/a/img/v1/75x75/i1/c170693/jean-paul-duminy.jpg", "country": "South Africa National Cricket Team "},
{"pname": "Andile Phehlukwayo", "img": "https://www.cricbuzz.com/a/img/v1/75x75/i1/c170694/andile-phehlukwayo.jpg", "country": "South Africa National Cricket Team "},
{"pname": "Tamim Iqbal", "img": "https://www.cricbuzz.com/a/img/v1/75x75/i1/c170899/tamim-iqbal.jpg", "country": "Bangladesh National Cricket Team "},
{"pname": "Soumya Sarkar", "img": "https://www.cricbuzz.com/a/img/v1/75x75/i1/c170900/soumya-sarkar.jpg", "country": "Bangladesh National Cricket Team "},
{"pname": "Sabbir Rahman", "img": "https://www.cricbuzz.com/a/img/v1/75x75/i1/c170903/sabbir-rahman.jpg", "country": "Bangladesh National Cricket Team "},
{"pname": "Mahmudullah", "img": "https://www.cricbuzz.com/a/img/v1/75x75/i1/c170905/mahmudullah.jpg", "country": "Bangladesh National Cricket Team "},
{"pname": "Shakib Al Hasan", "img": "https://www.cricbuzz.com/a/img/v1/75x75/i1/c170912/shakib-al-hasan.jpg", "country": "Bangladesh National Cricket Team "},
{"pname": "Mohammad Saifuddin", "img": "https://www.cricbuzz.com/a/img/v1/75x75/i1/c170907/mohammad-saifuddin.jpg", "country": "Bangladesh National Cricket Team "},
{"pname": "Mosaddek Hossain", "img": "https://www.cricbuzz.com/a/img/v1/75x75/i1/c170909/mosaddek-hossain.jpg", "country": "Bangladesh National Cricket Team "},
{"pname": "Jason Holder", "img": "https://www.cricbuzz.com/a/img/v1/75x75/i1/c170806/jason-holder.jpg", "country": "West Indies Cricket Team "},
{"pname": "Andre Russell", "img": "https://www.cricbuzz.com/a/img/v1/75x75/i1/c170821/andre-russell.jpg", "country": "West Indies Cricket Team "},
{"pname": "Carlos Brathwaite", "img": "https://www.cricbuzz.com/a/img/v1/75x75/i1/c170798/carlos-brathwaite.jpg", "country": "West Indies Cricket Team "},
{"pname": "Shai Hope", "img": "https://www.cricbuzz.com/a/img/v1/75x75/i1/c170814/shai-hope.jpg", "country": "West Indies Cricket Team "},
{"pname": "Nicholas Pooran", "img": "https://www.cricbuzz.com/a/img/v1/75x75/i1/c170810/nicholas-pooran.jpg", "country": "West Indies Cricket Team "},
{"pname": "Sheldon Cottrell", "img": "https://www.cricbuzz.com/a/img/v1/75x75/i1/c170828/sheldon-cottrell.jpg", "country": "West Indies Cricket Team "},
{"pname": "Shannon Gabriel", "img": "https://www.cricbuzz.com/a/img/v1/75x75/i1/c170826/shannon-gabriel.jpg", "country": "West Indies Cricket Team "},
{"pname": "Kemar Roach", "img": "https://www.cricbuzz.com/a/img/v1/75x75/i1/c170820/kemar-roach.jpg", "country": "West Indies Cricket Team "},
{"pname": "Ashley Nurse", "img": "https://www.cricbuzz.com/a/img/v1/75x75/i1/c170817/ashley-nurse.jpg", "country": "West Indies Cricket Team "},
{"pname": "Oshane Thomas", "img": "https://www.cricbuzz.com/a/img/v1/75x75/i1/c170824/oshane-thomas.jpg", "country": "West Indies Cricket Team "},
{"pname": "Dwaine Pretorius", "img": "https://www.cricbuzz.com/a/img/v1/75x75/i1/c170695/dwaine-pretorius.jpg", "country": "South Africa National Cricket Team "},
{"pname": "Chris Morris", "img": "https://www.cricbuzz.com/a/img/v1/75x75/i1/c170696/chris-morris.jpg", "country": "South Africa National Cricket Team "},
{"pname": "Mehidy Hasan", "img": "https://www.cricbuzz.com/a/img/v1/75x75/i1/c148289/mehidy-hasan.jpg", "country": "Bangladesh National Cricket Team "},
{"pname": "Mushfiqur Rahim", "img": "https://www.cricbuzz.com/a/img/v1/75x75/i1/c170916/mushfiqur-rahim.jpg", "country": "Bangladesh National Cricket Team "},
{"pname": "Liton Das", "img": "https://www.cricbuzz.com/a/img/v1/75x75/i1/c170914/liton-das.jpg", "country": "Bangladesh National Cricket Team "},
{"pname": "Mohammad Mithun", "img": "https://www.cricbuzz.com/a/img/v1/75x75/i1/c170918/mohammad-mithun.jpg", "country": "Bangladesh National Cricket Team "},
{"pname": "Mashrafe Mortaza", "img": "https://www.cricbuzz.com/a/img/v1/75x75/i1/c170920/mashrafe-mortaza.jpg", "country": "Bangladesh National Cricket Team "},
{"pname": "Rubel Hossain", "img": "https://www.cricbuzz.com/a/img/v1/75x75/i1/c170922/rubel-hossain.jpg", "country": "Bangladesh National Cricket Team "},
{"pname": "Mustafizur Rahman", "img": "https://www.cricbuzz.com/a/img/v1/75x75/i1/c170925/mustafizur-rahman.jpg", "country": "Bangladesh National Cricket Team "},
{"pname": "Abu Jayed", "img": "https://www.cricbuzz.com/a/img/v1/75x75/i1/c170927/abu-jayed.jpg", "country": "Bangladesh National Cricket Team "},
{"pname": "Quinton de Kock", "img": "https://www.cricbuzz.com/a/img/v1/75x75/i1/c170698/quinton-de-kock.jpg", "country": "South Africa National Cricket Team "},
{"pname": "Imran Tahir", "img": "https://www.cricbuzz.com/a/img/v1/75x75/i1/c170764/imran-tahir.jpg", "country": "South Africa National Cricket Team "},
{"pname": "Kagiso Rabada", "img": "https://www.cricbuzz.com/a/img/v1/75x75/i1/c170759/kagiso-rabada.jpg", "country": "South Africa National Cricket Team "},
{"pname": "Lungi Ngidi", "img": "https://www.cricbuzz.com/a/img/v1/75x75/i1/c170761/lungi-ngidi.jpg", "country": "South Africa National Cricket Team "},
{"pname": "Tabraiz Shamsi", "img": "https://www.cricbuzz.com/a/img/v1/75x75/i1/c170774/tabraiz-shamsi.jpg", "country": "South Africa National Cricket Team "},
{"pname": "Beuran Hendricks", "img": "https://www.cricbuzz.com/a/img/v1/75x75/i1/c157349/beuran-hendricks.jpg", "country": "South Africa National Cricket Team "},
{"pname": "Asghar Afghan", "img": "https://www.cricbuzz.com/a/img/v1/75x75/i1/c170835/asghar-afghan.jpg", "country": "Afghanistan National Cricket Team "},
{"pname": "Hashmatullah Shahidi", "img": "https://www.cricbuzz.com/a/img/v1/75x75/i1/c170837/hashmatullah-shahidi.jpg", "country": "Afghanistan National Cricket Team "},
{"pname": "Hazratullah Zazai", "img": "https://www.cricbuzz.com/a/img/v1/75x75/i1/c170833/hazratullah-zazai.jpg", "country": "Afghanistan National Cricket Team "},
{"pname": "Najibullah Zadran", "img": "https://www.cricbuzz.com/a/img/v1/75x75/i1/c170839/najibullah-zadran.jpg", "country": "Afghanistan National Cricket Team "},
{"pname": "Noor Ali Zadran", "img": "https://www.cricbuzz.com/a/img/v1/75x75/i1/c170831/noor-ali-zadran.jpg", "country": "Afghanistan National Cricket Team "},
{"pname": "Rahmat Shah", "img": "https://www.cricbuzz.com/a/img/v1/75x75/i1/c170846/rahmat-shah.jpg", "country": "Afghanistan National Cricket Team "},
{"pname": "Samiullah Shinwari", "img": "https://www.cricbuzz.com/a/img/v1/75x75/i1/c170849/samiullah-shinwari.jpg", "country": "Afghanistan National Cricket Team "},
{"pname": "Gulbadin Naib", "img": "https://www.cricbuzz.com/a/img/v1/75x75/i1/c170851/gulbadin-naib.jpg", "country": "Afghanistan National Cricket Team "},
{"pname": "Mohammad Nabi", "img": "https://www.cricbuzz.com/a/img/v1/75x75/i1/c170853/mohammad-nabi.jpg", "country": "Afghanistan National Cricket Team "},
{"pname": "Mohammad Shahzad", "img": "https://www.cricbuzz.com/a/img/v1/75x75/i1/c170855/mohammad-shahzad.jpg", "country": "Afghanistan National Cricket Team "},
{"pname": "Aftab Alam", "img": "https://www.cricbuzz.com/a/img/v1/75x75/i1/c170861/aftab-alam.jpg", "country": "Afghanistan National Cricket Team "},
{"pname": "Dawlat Zadran", "img": "https://www.cricbuzz.com/a/img/v1/75x75/i1/c170859/dawlat-zadran.jpg", "country": "Afghanistan National Cricket Team "},
{"pname": "Hamid Hassan", "img": "https://www.cricbuzz.com/a/img/v1/75x75/i1/c170863/hamid-hassan.jpg", "country": "Afghanistan National Cricket Team "},
{"pname": "Rashid Khan", "img": "https://www.cricbuzz.com/a/img/v1/75x75/i1/c170857/rashid-khan.jpg", "country": "Afghanistan National Cricket Team "},
{"pname": "Mujeeb Ur Rahman", "img": "https://www.cricbuzz.com/a/img/v1/75x75/i1/c170865/mujeeb-ur-rahman.jpg", "country": "Afghanistan National Cricket Team "},
{"pname": "Martin Guptill", "img": "https://www.cricbuzz.com/a/img/v1/75x75/i1/c170731/martin-guptill.jpg", "country": "New Zealand National Cricket Team "},
{"pname": "Ross Taylor", "img": "https://www.cricbuzz.com/a/img/v1/75x75/i1/c170729/ross-taylor.jpg", "country": "New Zealand National Cricket Team "},
{"pname": "Kane Williamson", "img": "https://www.cricbuzz.com/a/img/v1/75x75/i1/c170733/kane-williamson.jpg", "country": "New Zealand National Cricket Team "},
{"pname": "James Neesham", "img": "https://www.cricbuzz.com/a/img/v1/75x75/i1/c170739/james-neesham.jpg", "country": "New Zealand National Cricket Team "},
{"pname": "Colin de Grandhomme", "img": "https://www.cricbuzz.com/a/img/v1/75x75/i1/c170735/colin-de-grandhomme.jpg", "country": "New Zealand National Cricket Team "},
{"pname": "Colin Munro", "img": "https://www.cricbuzz.com/a/img/v1/75x75/i1/c170737/colin-munro.jpg", "country": "New Zealand National Cricket Team "},
{"pname": "Mitchell Santner", "img": "https://www.cricbuzz.com/a/img/v1/75x75/i1/c170741/mitchell-santner.jpg", "country": "New Zealand National Cricket Team "},
{"pname": "Tom Latham", "img": "https://www.cricbuzz.com/a/img/v1/75x75/i1/c170743/tom-latham.jpg", "country": "New Zealand National Cricket Team "},
{"pname": "Henry Nicholls", "img": "https://www.cricbuzz.com/a/img/v1/75x75/i1/c170745/henry-nicholls.jpg", "country": "New Zealand National Cricket Team "},
{"pname": "Tom Blundell", "img": "https://www.cricbuzz.com/a/img/v1/75x75/i1/c170757/tom-blundell.jpg", "country": "New Zealand National Cricket Team "},
{"pname": "Trent Boult", "img": "https://www.cricbuzz.com/a/img/v1/75x75/i1/c170747/trent-boult.jpg", "country": "New Zealand National Cricket Team "},
{"pname": "Matt Henry", "img": "https://www.cricbuzz.com/a/img/v1/75x75/i1/c170751/matt-henry.jpg", "country": "New Zealand National Cricket Team "},
{"pname": "Tim Southee", "img": "https://www.cricbuzz.com/a/img/v1/75x75/i1/c170753/tim-southee.jpg", "country": "New Zealand National Cricket Team "},
{"pname": "Ish Sodhi", "img": "https://www.cricbuzz.com/a/img/v1/75x75/i1/c170755/ish-sodhi.jpg", "country": "New Zealand National Cricket Team "},
{"pname": "Lockie Ferguson", "img": "https://www.cricbuzz.com/a/img/v1/75x75/i1/c170749/lockie-ferguson.jpg", "country": "New Zealand National Cricket Team "},
{"pname": "Eoin Morgan", "img": "https://www.cricbuzz.com/a/img/v1/75x75/i1/c170936/eoin-morgan.jpg", "country": "England National Cricket Team "},
{"pname": "Joe Root", "img": "https://www.cricbuzz.com/a/img/v1/75x75/i1/c170942/joe-root.jpg", "country": "England National Cricket Team "},
{"pname": "Jason Roy", "img": "https://www.cricbuzz.com/a/img/v1/75x75/i1/c170941/jason-roy.jpg", "country": "England National Cricket Team "},
{"pname": "James Vince", "img": "https://www.cricbuzz.com/a/img/v1/75x75/i1/c170945/james-vince.jpg", "country": "England National Cricket Team "},
{"pname": "Moeen Ali", "img": "https://www.cricbuzz.com/a/img/v1/75x75/i1/c170953/moeen-ali.jpg", "country": "England National Cricket Team "},
{"pname": "Ben Stokes", "img": "https://www.cricbuzz.com/a/img/v1/75x75/i1/c170950/ben-stokes.jpg", "country": "England National Cricket Team "},
{"pname": "Chris Woakes", "img": "https://www.cricbuzz.com/a/img/v1/75x75/i1/c170964/chris-woakes.jpg", "country": "England National Cricket Team "},
{"pname": "Tom Curran", "img": "https://www.cricbuzz.com/a/img/v1/75x75/i1/c170967/tom-curran.jpg", "country": "England National Cricket Team "},
{"pname": "Liam Dawson", "img": "https://www.cricbuzz.com/a/img/v1/75x75/i1/c170968/liam-dawson.jpg", "country": "England National Cricket Team "},
{"pname": "Jofra Archer", "img": "https://www.cricbuzz.com/a/img/v1/75x75/i1/c170970/jofra-archer.jpg", "country": "England National Cricket Team "},
{"pname": "Jonny Bairstow", "img": "https://www.cricbuzz.com/a/img/v1/75x75/i1/c170976/jonny-bairstow.jpg", "country": "England National Cricket Team "},
{"pname": "Jos Buttler", "img": "https://www.cricbuzz.com/a/img/v1/75x75/i1/c170980/jos-buttler.jpg", "country": "England National Cricket Team "},
{"pname": "Liam Plunkett", "img": "https://www.cricbuzz.com/a/img/v1/75x75/i1/c170983/liam-plunkett.jpg", "country": "England National Cricket Team "},
{"pname": "Adil Rashid", "img": "https://www.cricbuzz.com/a/img/v1/75x75/i1/c170987/adil-rashid.jpg", "country": "England National Cricket Team "},
{"pname": "Mark Wood", "img": "https://www.cricbuzz.com/a/img/v1/75x75/i1/c170990/mark-wood.jpg", "country": "England National Cricket Team "},
{"pname": "Aaron Finch", "img": "https://www.cricbuzz.com/a/img/v1/75x75/i1/c170630/aaron-finch.jpg", "country": "Australia National Cricket Team "},
{"pname": "Shaun Marsh", "img": "https://www.cricbuzz.com/a/img/v1/75x75/i1/c170626/shaun-marsh.jpg", "country": "Australia National Cricket Team "},
{"pname": "Steven Smith", "img": "https://www.cricbuzz.com/a/img/v1/75x75/i1/c170624/steven-smith.jpg", "country": "Australia National Cricket Team "},
{"pname": "David Warner", "img": "https://www.cricbuzz.com/a/img/v1/75x75/i1/c170635/david-warner.jpg", "country": "Australia National Cricket Team "},
{"pname": "Usman Khawaja", "img": "https://www.cricbuzz.com/a/img/v1/75x75/i1/c170640/usman-khawaja.jpg", "country": "Australia National Cricket Team "},
{"pname": "Glenn Maxwell", "img": "https://www.cricbuzz.com/a/img/v1/75x75/i1/c170641/glenn-maxwell.jpg", "country": "Australia National Cricket Team "},
{"pname": "Marcus Stoinis", "img": "https://www.cricbuzz.com/a/img/v1/75x75/i1/c176605/marcus-stoinis.jpg", "country": "Australia National Cricket Team "},
{"pname": "Alex Carey", "img": "https://www.cricbuzz.com/a/img/v1/75x75/i1/c170667/alex-carey.jpg", "country": "Australia National Cricket Team "},
{"pname": "Pat Cummins", "img": "https://www.cricbuzz.com/a/img/v1/75x75/i1/c170651/pat-cummins.jpg", "country": "Australia National Cricket Team "},
{"pname": "Nathan Lyon", "img": "https://www.cricbuzz.com/a/img/v1/75x75/i1/c170650/nathan-lyon.jpg", "country": "Australia National Cricket Team "},
{"pname": "Mitchell Starc", "img": "https://www.cricbuzz.com/a/img/v1/75x75/i1/c170643/mitchell-starc.jpg", "country": "Australia National Cricket Team "},
{"pname": "Kane Richardson", "img": "https://www.cricbuzz.com/a/img/v1/75x75/i1/c170638/kane-richardson.jpg", "country": "Australia National Cricket Team "},
{"pname": "Nathan Coulter-Nile", "img": "https://www.cricbuzz.com/a/img/v1/75x75/i1/c170648/nathan-coulter-nile.jpg", "country": "Australia National Cricket Team "},
{"pname": "Jason Behrendorff", "img": "https://www.cricbuzz.com/a/img/v1/75x75/i1/c170647/jason-behrendorff.jpg", "country": "Australia National Cricket Team "},
{"pname": "Adam Zampa", "img": "https://www.cricbuzz.com/a/img/v1/75x75/i1/c170654/adam-zampa.jpg", "country": "Australia National Cricket Team "},
{"pname": "Fakhar Zaman", "img": "https://www.cricbuzz.com/a/img/v1/75x75/i1/c170763/fakhar-zaman.jpg", "country": "Pakistan National Cricket Team "},
{"pname": "Imam-ul-Haq", "img": "https://www.cricbuzz.com/a/img/v1/75x75/i1/c170765/imam-ul-haq.jpg", "country": "Pakistan National Cricket Team "},
{"pname": "Babar Azam", "img": "https://www.cricbuzz.com/a/img/v1/75x75/i1/c170768/babar-azam.jpg", "country": "Pakistan National Cricket Team "},
{"pname": "Asif Ali", "img": "https://www.cricbuzz.com/a/img/v1/75x75/i1/c170770/asif-ali.jpg", "country": "Pakistan National Cricket Team "},
{"pname": "Haris Sohail", "img": "https://www.cricbuzz.com/a/img/v1/75x75/i1/c170777/haris-sohail.jpg", "country": "Pakistan National Cricket Team "},
{"pname": "Mohammad Hafeez", "img": "https://www.cricbuzz.com/a/img/v1/75x75/i1/c170776/mohammad-hafeez.jpg", "country": "Pakistan National Cricket Team "},
{"pname": "Shoaib Malik", "img": "https://www.cricbuzz.com/a/img/v1/75x75/i1/c170775/shoaib-malik.jpg", "country": "Pakistan National Cricket Team "},
{"pname": "Shadab Khan", "img": "https://www.cricbuzz.com/a/img/v1/75x75/i1/c170779/shadab-khan.jpg", "country": "Pakistan National Cricket Team "},
{"pname": "Imad Wasim", "img": "https://www.cricbuzz.com/a/img/v1/75x75/i1/c170782/imad-wasim.jpg", "country": "Pakistan National Cricket Team "},
{"pname": "Sarfaraz Ahmed", "img": "https://www.cricbuzz.com/a/img/v1/75x75/i1/c170787/sarfaraz-ahmed.jpg", "country": "Pakistan National Cricket Team "},
{"pname": "Wahab Riaz", "img": "https://www.cricbuzz.com/a/img/v1/75x75/i1/c170809/wahab-riaz.jpg", "country": "Pakistan National Cricket Team "},
{"pname": "Shaheen Afridi", "img": "https://www.cricbuzz.com/a/img/v1/75x75/i1/c170802/shaheen-afridi.jpg", "country": "Pakistan National Cricket Team "},
{"pname": "Hasan Ali", "img": "https://www.cricbuzz.com/a/img/v1/75x75/i1/c170804/hasan-ali.jpg", "country": "Pakistan National Cricket Team "},
{"pname": "Mohammad Hasnain", "img": "https://www.cricbuzz.com/a/img/v1/75x75/i1/c170805/mohammad-hasnain.jpg", "country": "Pakistan National Cricket Team "},
{"pname": "Mohammad Amir", "img": "https://www.cricbuzz.com/a/img/v1/75x75/i1/c170813/mohammad-amir.jpg", "country": "Pakistan National Cricket Team "}
]